TikTokDownload/TikTokDownload.py
TikTokDownload/TikTokMulti.py
TikTokDownload/__init__.py
__init__/TikTokDownload.py
__init__/TikTokMulti.py
__init__/__init__.py
TikTokDownload-1.2.3.dist-info/LICENSE
TikTokDownload-1.2.3.dist-info/METADATA
TikTokDownload-1.2.3.dist-info/WHEEL
TikTokDownload-1.2.3.dist-info/top_level.txt
TikTokDownload-1.2.3.dist-info/RECORD
